pytest_ptera/__init__.py
pytest_ptera/main.py
pytest_ptera/version.py
pytest_ptera-0.3.0.dist-info/entry_points.txt
pytest_ptera-0.3.0.dist-info/WHEEL
pytest_ptera-0.3.0.dist-info/METADATA
pytest_ptera-0.3.0.dist-info/RECORD
